{
    "score": 0,
    "total_indicators_possible": 10,
    "active_indicators_count": 0,
    "active_indicators": {},
    "category_reasoning": {
        "econ": "API错误: 400",
        "mil": "API错误: 400",
        "pol": "API错误: 400",
        "local": "API错误: 400"
    },
    "news_sources": {
        "econ": [
            {
                "title": "前飞书表格技术负责人创业：用AI表格嵌入一切，“喂养”AI丨涌现新项目",
                "source": "NewsAPI / 36kr.com",
                "date": "2026-02-09",
                "url": "https://36kr.com/p/3675553046831752"
            },
            {
                "title": "医美的钱都被谁赚了？",
                "source": "NewsAPI / 36kr.com",
                "date": "2026-02-09",
                "url": "https://36kr.com/p/3675420774310528"
            },
            {
                "title": "【IT之家评测室】超长续航 + 翻转设计，微星尊爵 14 Flip AI+ 2026 笔记本评测",
                "source": "NewsAPI / Ithome.com",
                "date": "2026-02-09",
                "url": "https://www.ithome.com/0/920/374.htm"
            },
            {
                "title": "布局汽车及零部件全球跨境电商平台，一汽解放 × 菜鸟达成战略合作",
                "source": "NewsAPI / Ithome.com",
                "date": "2026-02-09",
                "url": "https://www.ithome.com/0/920/347.htm"
            },
            {
                "title": "从香港“伴手礼”到内地15家门店，线香品牌「Sagrada Madre」用自然生命力切开中国市场",
                "source": "NewsAPI / 36kr.com",
                "date": "2026-02-09",
                "url": "https://36kr.com/p/3669714134704777"
            }
        ],
        "mil": [
            {
                "title": "前飞书表格技术负责人创业：用AI表格嵌入一切，“喂养”AI丨涌现新项目",
                "source": "NewsAPI / 36kr.com",
                "date": "2026-02-09",
                "url": "https://36kr.com/p/3675553046831752"
            },
            {
                "title": "从香港“伴手礼”到内地15家门店，线香品牌「Sagrada Madre」用自然生命力切开中国市场",
                "source": "NewsAPI / 36kr.com",
                "date": "2026-02-09",
                "url": "https://36kr.com/p/3669714134704777"
            },
            {
                "title": "李南央评张又侠事件 蔡霞：习近平与中共必有一斗(图)",
                "source": "NewsAPI / Secretchina.com",
                "date": "2026-02-09",
                "url": "https://www.secretchina.com/news/gb/2026/02/09/1094626.html"
            },
            {
                "title": "8点1氪丨韩交易所误发超400亿美元比特币；全球手机均价首破2900元；微信恢复千问与元宝红包口令复制",
                "source": "NewsAPI / 36kr.com",
                "date": "2026-02-08",
                "url": "https://36kr.com/p/3675308250506115"
            },
            {
                "title": "微信恢复千问与元宝红包口令复制；央视起底征信修复灰产链；苹果 2026 春季新品攻势揭幕；专家提醒“明星 AI 拜年”视频存在法律风险...",
                "source": "NewsAPI / Ithome.com",
                "date": "2026-02-08",
                "url": "https://www.ithome.com/0/920/325.htm"
            },
            {
                "title": "2026年2月9日外交部发言人林剑主持例行记者会_中华人民共和国外交部 - mfa.gov.cn",
                "source": "官方信源 / 外交部/国防部",
                "date": "2026-02-09",
                "url": "https://news.google.com/rss/articles/CBMidkFVX3lxTFBqUy12M1VCN193UGFOUjVMdW50UERuOXlYQ0g3NlVseDd4YXhreFgxZGVFTk0zWl96R1NVV0xVcGhhejREcGRhc09KVW1yMlllWW9ZbEZjRnl2dlR5TTRTb1hPOG5iNHV2UWVEM0lmMTJSX1VJM3c?oc=5"
            },
            {
                "title": "权威发布 - 中华人民共和国国防部",
                "source": "官方信源 / 外交部/国防部",
                "date": "2023-02-10",
                "url": "https://news.google.com/rss/articles/CBMiVEFVX3lxTE9rS0FCUzNPbDNHdFVmdS1fbF9kSTdHZXpJVE5vR3E4Yk95dzRSTVZFWFlaUkFGVHptdXBGOWJMRWd5ZTZGbHdYY2d0WlhBN0E5cnB4ZA?oc=5"
            },
            {
                "title": "驻外报道 - mfa.gov.cn",
                "source": "官方信源 / 外交部/国防部",
                "date": "2021-12-03",
                "url": "https://news.google.com/rss/articles/CBMiW0FVX3lxTFBzWmlLclhjbDZRRDBjYk1wc3c4bjYtWXg5NU9qazktNmFJUVBuZXF0ejhlaFlCMzJvd1dXWVRMTldHU3E3YjVBU1IyRzB4MGtXT3YzeUJGSHNiTU0?oc=5"
            },
            {
                "title": "春节聚餐别贪嘴，谨防神经血管“超负荷” - 中国军网",
                "source": "官方信源 / 解放军报/军网",
                "date": "2026-02-09",
                "url": "https://news.google.com/rss/articles/CBMiUkFVX3lxTE9wSWR4bzFUMUE4VTNXT3ZNNTA0OFFMWmxuNVhBRUhZZV9fTld2cVFzbld3ajJVODdZUzdTbE5hYnJiYlAzRFpmQUMwR1Y1Tmd0OEE?oc=5"
            },
            {
                "title": "“一国两制”下香港维护国家安全的实践白皮书|“一国两制”下香港维护国家安全的实践 - 中国军网",
                "source": "官方信源 / 解放军报/军网",
                "date": "2026-02-10",
                "url": "https://news.google.com/rss/articles/CBMiUkFVX3lxTFB4NTlwbDNpaXVIbWFHSldoODMxeXNscU40M1RTZEp6d2JMemwwemdya3RxTDY1ZEl0ZWRnTFVydFk2MVBxLVFZWkRGZlBuejBudXc?oc=5"
            },
            {
                "title": "日本将举行首相指名选举 - 中国军网",
                "source": "官方信源 / 解放军报/军网",
                "date": "2026-02-10",
                "url": "https://news.google.com/rss/articles/CBMiUkFVX3lxTE1TaWZ5b3hEQlczVnphYkl2dUpDRlBfd0Iwb0k0dW5LY29SaHU2UlM4REh5OTNZZzUzMkdpbEJuX1U5cEl6UXBtZmpndW0yQWZidGc?oc=5"
            }
        ],
        "pol": [
            {
                "title": "前飞书表格技术负责人创业：用AI表格嵌入一切，“喂养”AI丨涌现新项目",
                "source": "NewsAPI / 36kr.com",
                "date": "2026-02-09",
                "url": "https://36kr.com/p/3675553046831752"
            },
            {
                "title": "医美的钱都被谁赚了？",
                "source": "NewsAPI / 36kr.com",
                "date": "2026-02-09",
                "url": "https://36kr.com/p/3675420774310528"
            },
            {
                "title": "【IT之家评测室】超长续航 + 翻转设计，微星尊爵 14 Flip AI+ 2026 笔记本评测",
                "source": "NewsAPI / Ithome.com",
                "date": "2026-02-09",
                "url": "https://www.ithome.com/0/920/374.htm"
            },
            {
                "title": "达成里程碑：理想汽车超充站正式落地 4000 站",
                "source": "NewsAPI / Ithome.com",
                "date": "2026-02-09",
                "url": "https://www.ithome.com/0/920/357.htm"
            },
            {
                "title": "从香港“伴手礼”到内地15家门店，线香品牌「Sagrada Madre」用自然生命力切开中国市场",
                "source": "NewsAPI / 36kr.com",
                "date": "2026-02-09",
                "url": "https://36kr.com/p/3669714134704777"
            },
            {
                "title": "2026年2月9日外交部发言人林剑主持例行记者会_中华人民共和国外交部 - mfa.gov.cn",
                "source": "官方信源 / 外交部/国防部",
                "date": "2026-02-09",
                "url": "https://news.google.com/rss/articles/CBMidkFVX3lxTFBqUy12M1VCN193UGFOUjVMdW50UERuOXlYQ0g3NlVseDd4YXhreFgxZGVFTk0zWl96R1NVV0xVcGhhejREcGRhc09KVW1yMlllWW9ZbEZjRnl2dlR5TTRTb1hPOG5iNHV2UWVEM0lmMTJSX1VJM3c?oc=5"
            },
            {
                "title": "权威发布 - 中华人民共和国国防部",
                "source": "官方信源 / 外交部/国防部",
                "date": "2023-02-10",
                "url": "https://news.google.com/rss/articles/CBMiVEFVX3lxTE9rS0FCUzNPbDNHdFVmdS1fbF9kSTdHZXpJVE5vR3E4Yk95dzRSTVZFWFlaUkFGVHptdXBGOWJMRWd5ZTZGbHdYY2d0WlhBN0E5cnB4ZA?oc=5"
            },
            {
                "title": "驻外报道 - mfa.gov.cn",
                "source": "官方信源 / 外交部/国防部",
                "date": "2021-12-03",
                "url": "https://news.google.com/rss/articles/CBMiW0FVX3lxTFBzWmlLclhjbDZRRDBjYk1wc3c4bjYtWXg5NU9qazktNmFJUVBuZXF0ejhlaFlCMzJvd1dXWVRMTldHU3E3YjVBU1IyRzB4MGtXT3YzeUJGSHNiTU0?oc=5"
            },
            {
                "title": "春节聚餐别贪嘴，谨防神经血管“超负荷” - 中国军网",
                "source": "官方信源 / 解放军报/军网",
                "date": "2026-02-09",
                "url": "https://news.google.com/rss/articles/CBMiUkFVX3lxTE9wSWR4bzFUMUE4VTNXT3ZNNTA0OFFMWmxuNVhBRUhZZV9fTld2cVFzbld3ajJVODdZUzdTbE5hYnJiYlAzRFpmQUMwR1Y1Tmd0OEE?oc=5"
            },
            {
                "title": "“一国两制”下香港维护国家安全的实践白皮书|“一国两制”下香港维护国家安全的实践 - 中国军网",
                "source": "官方信源 / 解放军报/军网",
                "date": "2026-02-10",
                "url": "https://news.google.com/rss/articles/CBMiUkFVX3lxTFB4NTlwbDNpaXVIbWFHSldoODMxeXNscU40M1RTZEp6d2JMemwwemdya3RxTDY1ZEl0ZWRnTFVydFk2MVBxLVFZWkRGZlBuejBudXc?oc=5"
            },
            {
                "title": "日本将举行首相指名选举 - 中国军网",
                "source": "官方信源 / 解放军报/军网",
                "date": "2026-02-10",
                "url": "https://news.google.com/rss/articles/CBMiUkFVX3lxTE1TaWZ5b3hEQlczVnphYkl2dUpDRlBfd0Iwb0k0dW5LY29SaHU2UlM4REh5OTNZZzUzMkdpbEJuX1U5cEl6UXBtZmpndW0yQWZidGc?oc=5"
            }
        ],
        "local": []
    },
    "last_updated": "2026-02-10T05:49:17.599807+00:00"
}